transfer/__init__.py
transfer/__version__.py
transfer/cli.py
transfer/main.py
transfer/mk_method_names.py
transfer/.ruff_cache/.gitignore
transfer/.ruff_cache/CACHEDIR.TAG
transfer/.ruff_cache/0.5.1/15026493043125062528
transfer/public/__init__.py
transfer/public/dde_control_center_public_method.py
transfer/public/dde_desktop_public_method.py
transfer/public/dde_dock_public_method.py
transfer/public/dde_launcher_public_method.py
transfer/public/right_menu_public_method.py
transfer/tpl/.env
transfer/tpl/requirements.txt
transfer/tpl/ruff.toml
youqu2_transfer_youqu3-2024.7.12.dist-info/METADATA
youqu2_transfer_youqu3-2024.7.12.dist-info/WHEEL
youqu2_transfer_youqu3-2024.7.12.dist-info/entry_points.txt
youqu2_transfer_youqu3-2024.7.12.dist-info/licenses/LICENSE
youqu2_transfer_youqu3-2024.7.12.dist-info/RECORD
